tuneinsight/README.md
tuneinsight/__init__.py
tuneinsight/api/__init__.py
tuneinsight/api/api-checksum
tuneinsight/api/sdk/__init__.py
tuneinsight/api/sdk/api/__init__.py
tuneinsight/api/sdk/api/api_admin/__init__.py
tuneinsight/api/sdk/api/api_admin/get_config.py
tuneinsight/api/sdk/api/api_admin/get_settings.py
tuneinsight/api/sdk/api/api_admin/patch_settings.py
tuneinsight/api/sdk/api/api_admin/post_storage.py
tuneinsight/api/sdk/api/api_computations/__init__.py
tuneinsight/api/sdk/api/api_computations/compute.py
tuneinsight/api/sdk/api/api_computations/delete_comp_bookmark.py
tuneinsight/api/sdk/api/api_computations/delete_computation.py
tuneinsight/api/sdk/api/api_computations/delete_computations.py
tuneinsight/api/sdk/api/api_computations/delete_result.py
tuneinsight/api/sdk/api/api_computations/documentation.py
tuneinsight/api/sdk/api/api_computations/get_comp_bookmark_list.py
tuneinsight/api/sdk/api/api_computations/get_computation.py
tuneinsight/api/sdk/api/api_computations/get_computation_list.py
tuneinsight/api/sdk/api/api_computations/get_params.py
tuneinsight/api/sdk/api/api_computations/get_preprocessing_dry_run.py
tuneinsight/api/sdk/api/api_computations/get_result.py
tuneinsight/api/sdk/api/api_computations/get_result_list.py
tuneinsight/api/sdk/api/api_computations/get_result_tag_list.py
tuneinsight/api/sdk/api/api_computations/init_session.py
tuneinsight/api/sdk/api/api_computations/patch_result.py
tuneinsight/api/sdk/api/api_computations/put_comp_bookmark.py
tuneinsight/api/sdk/api/api_computations/release_result.py
tuneinsight/api/sdk/api/api_datagen/__init__.py
tuneinsight/api/sdk/api/api_datagen/post_mock_dataset.py
tuneinsight/api/sdk/api/api_datagen/post_synthetic_dataset.py
tuneinsight/api/sdk/api/api_dataobject/__init__.py
tuneinsight/api/sdk/api/api_dataobject/delete_data_object.py
tuneinsight/api/sdk/api/api_dataobject/delete_data_objects.py
tuneinsight/api/sdk/api/api_dataobject/get_data_object.py
tuneinsight-0.14.1.dist-info/METADATA
tuneinsight-0.14.1.dist-info/WHEEL
tuneinsight-0.14.1.dist-info/entry_points.txt
tuneinsight-0.14.1.dist-info/RECORD
