Metadata-Version: 2.1
Name: tuneinsight
Version: 0.14.1
Summary: Official Python SDK for the Tune Insight API. The current version is compatible with the same version of the API.
License: Apache-2.0
Author: Tune Insight SA
Requires-Python: >=3.9,<4.0
Classifier: License :: OSI Approved :: Apache Software License
Classifier: Programming Language :: Python :: 3
Classifier: Programming Language :: Python :: 3.9
Classifier: Programming Language :: Python :: 3.10
Classifier: Programming Language :: Python :: 3.11
Classifier: Programming Language :: Python :: 3.12
Requires-Dist: PyYAML (>=6.0,<7.0)
Requires-Dist: attrs (>=21.3.0)
Requires-Dist: black (==24.2.0)
Requires-Dist: certifi (>=2023.7.22,<2024.0.0)
Requires-Dist: httpx (>=0.15.4,<0.24.0)
Requires-Dist: jupyter (>=1.1.1,<2.0.0)
Requires-Dist: matplotlib (>=3.5.0,<4.0.0)
Requires-Dist: notebook (>=6.4.11,<7.0.0)
Requires-Dist: pandas (>=2.2.3,<3.0.0)
Requires-Dist: python-dateutil (>=2.8.0,<3.0.0)
Requires-Dist: python-dotenv (>=0.21.0,<0.22.0)
Requires-Dist: python-keycloak (>=3.9.0,<4.0.0)
Requires-Dist: tqdm (>=4.66.4,<5.0.0)
Requires-Dist: typing-extensions (>=4.6.3,<5.0.0)
